{
    "SVC": {
        "5": {
            "test throw median": {
                "balanced_accuracy": {
                    "test": 0.484,
                    "train": 1.0
                },
                "accuracy": {
                    "test": 0.5,
                    "train": 1.0
                },
                "f1_weighted": {
                    "test": 0.51,
                    "train": 1.0
                },
                "roc_auc_ovr_weighted": {
                    "test": 0.484,
                    "train": 1.0
                }
            },
            "keep median": {
                "balanced_accuracy": {
                    "test": 0.459,
                    "train": 0.912
                },
                "accuracy": {
                    "test": 0.464,
                    "train": 0.913
                },
                "f1_weighted": {
                    "test": 0.482,
                    "train": 0.913
                },
                "roc_auc_ovr_weighted": {
                    "test": 0.459,
                    "train": 0.912
                }
            }
        },
        "10": {
            "test throw median": {
                "balanced_accuracy": {
                    "test": 0.585,
                    "train": 0.907
                },
                "accuracy": {
                    "test": 0.579,
                    "train": 0.904
                },
                "f1_weighted": {
                    "test": 0.581,
                    "train": 0.904
                },
                "roc_auc_ovr_weighted": {
                    "test": 0.585,
                    "train": 0.907
                }
            },
            "keep median": {
                "balanced_accuracy": {
                    "test": 0.429,
                    "train": 0.829
                },
                "accuracy": {
                    "test": 0.429,
                    "train": 0.825
                },
                "f1_weighted": {
                    "test": 0.426,
                    "train": 0.826
                },
                "roc_auc_ovr_weighted": {
                    "test": 0.429,
                    "train": 0.829
                }
            }
        },
        "50": {
            "test throw median": {
                "balanced_accuracy": {
                    "test": 0.455,
                    "train": 0.973
                },
                "accuracy": {
                    "test": 0.455,
                    "train": 0.968
                },
                "f1_weighted": {
                    "test": 0.312,
                    "train": 0.968
                },
                "roc_auc_ovr_weighted": {
                    "test": 0.455,
                    "train": 0.973
                }
            },
            "keep median": {
                "balanced_accuracy": {
                    "test": 0.517,
                    "train": 0.699
                },
                "accuracy": {
                    "test": 0.464,
                    "train": 0.684
                },
                "f1_weighted": {
                    "test": 0.458,
                    "train": 0.678
                },
                "roc_auc_ovr_weighted": {
                    "test": 0.517,
                    "train": 0.699
                }
            }
        },
        "100": {
            "test throw median": {
                "balanced_accuracy": {
                    "test": 0.364,
                    "train": 0.558
                },
                "accuracy": {
                    "test": 0.364,
                    "train": 0.559
                },
                "f1_weighted": {
                    "test": 0.358,
                    "train": 0.563
                },
                "roc_auc_ovr_weighted": {
                    "test": 0.364,
                    "train": 0.558
                }
            },
            "keep median": {
                "balanced_accuracy": {
                    "test": 0.542,
                    "train": 1.0
                },
                "accuracy": {
                    "test": 0.607,
                    "train": 1.0
                },
                "f1_weighted": {
                    "test": 0.491,
                    "train": 1.0
                },
                "roc_auc_ovr_weighted": {
                    "test": 0.542,
                    "train": 1.0
                }
            }
        }
    },
    "RF": {
        "5": {
            "test throw median": {
                "balanced_accuracy": {
                    "test": 0.438,
                    "train": 0.976
                },
                "accuracy": {
                    "test": 0.45,
                    "train": 0.978
                },
                "f1_weighted": {
                    "test": 0.454,
                    "train": 0.978
                },
                "roc_auc_ovr_weighted": {
                    "test": 0.438,
                    "train": 0.976
                }
            },
            "keep median": {
                "balanced_accuracy": {
                    "test": 0.464,
                    "train": 1.0
                },
                "accuracy": {
                    "test": 0.464,
                    "train": 1.0
                },
                "f1_weighted": {
                    "test": 0.458,
                    "train": 1.0
                },
                "roc_auc_ovr_weighted": {
                    "test": 0.464,
                    "train": 1.0
                }
            }
        },
        "10": {
            "test throw median": {
                "balanced_accuracy": {
                    "test": 0.583,
                    "train": 1.0
                },
                "accuracy": {
                    "test": 0.474,
                    "train": 1.0
                },
                "f1_weighted": {
                    "test": 0.395,
                    "train": 1.0
                },
                "roc_auc_ovr_weighted": {
                    "test": 0.583,
                    "train": 1.0
                }
            },
            "keep median": {
                "balanced_accuracy": {
                    "test": 0.491,
                    "train": 1.0
                },
                "accuracy": {
                    "test": 0.429,
                    "train": 1.0
                },
                "f1_weighted": {
                    "test": 0.429,
                    "train": 1.0
                },
                "roc_auc_ovr_weighted": {
                    "test": 0.491,
                    "train": 1.0
                }
            }
        },
        "50": {
            "test throw median": {
                "balanced_accuracy": {
                    "test": 0.536,
                    "train": 1.0
                },
                "accuracy": {
                    "test": 0.524,
                    "train": 1.0
                },
                "f1_weighted": {
                    "test": 0.489,
                    "train": 1.0
                },
                "roc_auc_ovr_weighted": {
                    "test": 0.536,
                    "train": 1.0
                }
            },
            "keep median": {
                "balanced_accuracy": {
                    "test": 0.464,
                    "train": 1.0
                },
                "accuracy": {
                    "test": 0.464,
                    "train": 1.0
                },
                "f1_weighted": {
                    "test": 0.403,
                    "train": 1.0
                },
                "roc_auc_ovr_weighted": {
                    "test": 0.464,
                    "train": 1.0
                }
            }
        },
        "100": {
            "test throw median": {
                "balanced_accuracy": {
                    "test": 0.353,
                    "train": 1.0
                },
                "accuracy": {
                    "test": 0.421,
                    "train": 1.0
                },
                "f1_weighted": {
                    "test": 0.432,
                    "train": 1.0
                },
                "roc_auc_ovr_weighted": {
                    "test": 0.353,
                    "train": 1.0
                }
            },
            "keep median": {
                "balanced_accuracy": {
                    "test": 0.467,
                    "train": 1.0
                },
                "accuracy": {
                    "test": 0.5,
                    "train": 1.0
                },
                "f1_weighted": {
                    "test": 0.357,
                    "train": 1.0
                },
                "roc_auc_ovr_weighted": {
                    "test": 0.467,
                    "train": 1.0
                }
            }
        }
    },
    "MLP": {
        "5": {
            "test throw median": {
                "balanced_accuracy": {
                    "test": 0.562,
                    "train": 1.0
                },
                "accuracy": {
                    "test": 0.556,
                    "train": 1.0
                },
                "f1_weighted": {
                    "test": 0.556,
                    "train": 1.0
                },
                "roc_auc_ovr_weighted": {
                    "test": 0.562,
                    "train": 1.0
                }
            },
            "keep median": {
                "balanced_accuracy": {
                    "test": 0.433,
                    "train": 1.0
                },
                "accuracy": {
                    "test": 0.429,
                    "train": 1.0
                },
                "f1_weighted": {
                    "test": 0.434,
                    "train": 1.0
                },
                "roc_auc_ovr_weighted": {
                    "test": 0.433,
                    "train": 1.0
                }
            }
        },
        "10": {
            "test throw median": {
                "balanced_accuracy": {
                    "test": 0.568,
                    "train": 1.0
                },
                "accuracy": {
                    "test": 0.571,
                    "train": 1.0
                },
                "f1_weighted": {
                    "test": 0.569,
                    "train": 1.0
                },
                "roc_auc_ovr_weighted": {
                    "test": 0.568,
                    "train": 1.0
                }
            },
            "keep median": {
                "balanced_accuracy": {
                    "test": 0.618,
                    "train": 1.0
                },
                "accuracy": {
                    "test": 0.607,
                    "train": 1.0
                },
                "f1_weighted": {
                    "test": 0.6,
                    "train": 1.0
                },
                "roc_auc_ovr_weighted": {
                    "test": 0.618,
                    "train": 1.0
                }
            }
        },
        "50": {
            "test throw median": {
                "balanced_accuracy": {
                    "test": 0.523,
                    "train": 1.0
                },
                "accuracy": {
                    "test": 0.526,
                    "train": 1.0
                },
                "f1_weighted": {
                    "test": 0.529,
                    "train": 1.0
                },
                "roc_auc_ovr_weighted": {
                    "test": 0.523,
                    "train": 1.0
                }
            },
            "keep median": {
                "balanced_accuracy": {
                    "test": 0.456,
                    "train": 0.932
                },
                "accuracy": {
                    "test": 0.357,
                    "train": 0.948
                },
                "f1_weighted": {
                    "test": 0.285,
                    "train": 0.947
                },
                "roc_auc_ovr_weighted": {
                    "test": 0.456,
                    "train": 0.932
                }
            }
        },
        "100": {
            "test throw median": {
                "balanced_accuracy": {
                    "test": 0.344,
                    "train": 1.0
                },
                "accuracy": {
                    "test": 0.292,
                    "train": 1.0
                },
                "f1_weighted": {
                    "test": 0.281,
                    "train": 1.0
                },
                "roc_auc_ovr_weighted": {
                    "test": 0.344,
                    "train": 1.0
                }
            },
            "keep median": {
                "balanced_accuracy": {
                    "test": 0.298,
                    "train": 1.0
                },
                "accuracy": {
                    "test": 0.286,
                    "train": 1.0
                },
                "f1_weighted": {
                    "test": 0.3,
                    "train": 1.0
                },
                "roc_auc_ovr_weighted": {
                    "test": 0.298,
                    "train": 1.0
                }
            }
        }
    }
}